[
  {
    "id": "06c461b6-b198-11ea-8c5f-0242ac110002",
    "name": "Validate Request",
    "assignee": "Maker",
    "created": "2020-06-18T19:15:09.490+0000",
    "due": null,
    "followUp": null,
    "delegationState": null,
    "description": null,
    "executionId": "06c43a9a-b198-11ea-8c5f-0242ac110002",
    "owner": null,
    "parentTaskId": null,
    "priority": 50,
    "processDefinitionId": "warranty_approval_test:6:8a3c1779-b08e-11ea-8c5f-0242ac110002",
    "processInstanceId": "06c43a9a-b198-11ea-8c5f-0242ac110002",
    "taskDefinitionKey": "Activity_1wukx49",
    "caseExecutionId": null,
    "caseInstanceId": null,
    "caseDefinitionId": null,
    "suspended": false,
    "formKey": null,
    "tenantId": null
  },
  {
    "id": "0c8e7efe-b195-11ea-8c5f-0242ac110002",
    "name": "Validate Request",
    "assignee": "Maker",
    "created": "2020-06-18T18:53:50.713+0000",
    "due": null,
    "followUp": null,
    "delegationState": null,
    "description": null,
    "executionId": "0c8e57e2-b195-11ea-8c5f-0242ac110002",
    "owner": null,
    "parentTaskId": null,
    "priority": 50,
    "processDefinitionId": "warranty_approval_test:6:8a3c1779-b08e-11ea-8c5f-0242ac110002",
    "processInstanceId": "0c8e57e2-b195-11ea-8c5f-0242ac110002",
    "taskDefinitionKey": "Activity_1wukx49",
    "caseExecutionId": null,
    "caseInstanceId": null,
    "caseDefinitionId": null,
    "suspended": false,
    "formKey": null,
    "tenantId": null
  },
  {
    "id": "0cc32a61-b19d-11ea-8c5f-0242ac110002",
    "name": "Validate Request",
    "assignee": "Maker",
    "created": "2020-06-18T19:51:07.032+0000",
    "due": null,
    "followUp": null,
    "delegationState": null,
    "description": null,
    "executionId": "0cc30345-b19d-11ea-8c5f-0242ac110002",
    "owner": null,
    "parentTaskId": null,
    "priority": 50,
    "processDefinitionId": "warranty_approval_test:6:8a3c1779-b08e-11ea-8c5f-0242ac110002",
    "processInstanceId": "0cc30345-b19d-11ea-8c5f-0242ac110002",
    "taskDefinitionKey": "Activity_1wukx49",
    "caseExecutionId": null,
    "caseInstanceId": null,
    "caseDefinitionId": null,
    "suspended": false,
    "formKey": null,
    "tenantId": null
  },
  {
    "id": "354aba31-b193-11ea-8c5f-0242ac110002",
    "name": "Validate Request",
    "assignee": "Maker",
    "created": "2020-06-18T18:40:40.062+0000",
    "due": null,
    "followUp": null,
    "delegationState": null,
    "description": null,
    "executionId": "354aba2a-b193-11ea-8c5f-0242ac110002",
    "owner": null,
    "parentTaskId": null,
    "priority": 50,
    "processDefinitionId": "warranty_approval_test:6:8a3c1779-b08e-11ea-8c5f-0242ac110002",
    "processInstanceId": "354aba2a-b193-11ea-8c5f-0242ac110002",
    "taskDefinitionKey": "Activity_1wukx49",
    "caseExecutionId": null,
    "caseInstanceId": null,
    "caseDefinitionId": null,
    "suspended": false,
    "formKey": null,
    "tenantId": null
  },
  {
    "id": "54debeba-b08e-11ea-8c5f-0242ac110002",
    "name": "Validate Request",
    "assignee": "Maker",
    "created": "2020-06-17T11:33:14.395+0000",
    "due": null,
    "followUp": null,
    "delegationState": null,
    "description": null,
    "executionId": "54debeb2-b08e-11ea-8c5f-0242ac110002",
    "owner": null,
    "parentTaskId": null,
    "priority": 50,
    "processDefinitionId": "warranty_approval_test:5:432b3091-b08e-11ea-8c5f-0242ac110002",
    "processInstanceId": "54debeb2-b08e-11ea-8c5f-0242ac110002",
    "taskDefinitionKey": "Activity_1wukx49",
    "caseExecutionId": null,
    "caseInstanceId": null,
    "caseDefinitionId": null,
    "suspended": false,
    "formKey": null,
    "tenantId": null
  },
  {
    "id": "77b333c8-b189-11ea-8c5f-0242ac110002",
    "name": "Validate Request",
    "assignee": "Maker",
    "created": "2020-06-18T17:30:56.509+0000",
    "due": null,
    "followUp": null,
    "delegationState": null,
    "description": null,
    "executionId": "77b30cac-b189-11ea-8c5f-0242ac110002",
    "owner": null,
    "parentTaskId": null,
    "priority": 50,
    "processDefinitionId": "warranty_approval_test:6:8a3c1779-b08e-11ea-8c5f-0242ac110002",
    "processInstanceId": "77b30cac-b189-11ea-8c5f-0242ac110002",
    "taskDefinitionKey": "Activity_1wukx49",
    "caseExecutionId": null,
    "caseInstanceId": null,
    "caseDefinitionId": null,
    "suspended": false,
    "formKey": null,
    "tenantId": null
  },
  {
    "id": "7d2ff63d-b195-11ea-8c5f-0242ac110002",
    "name": "Validate Request",
    "assignee": "Maker",
    "created": "2020-06-18T18:56:59.676+0000",
    "due": null,
    "followUp": null,
    "delegationState": null,
    "description": null,
    "executionId": "7d2fcf21-b195-11ea-8c5f-0242ac110002",
    "owner": null,
    "parentTaskId": null,
    "priority": 50,
    "processDefinitionId": "warranty_approval_test:6:8a3c1779-b08e-11ea-8c5f-0242ac110002",
    "processInstanceId": "7d2fcf21-b195-11ea-8c5f-0242ac110002",
    "taskDefinitionKey": "Activity_1wukx49",
    "caseExecutionId": null,
    "caseInstanceId": null,
    "caseDefinitionId": null,
    "suspended": false,
    "formKey": null,
    "tenantId": null
  },
  {
    "id": "a8664378-b19c-11ea-8c5f-0242ac110002",
    "name": "Validate Request",
    "assignee": "Maker",
    "created": "2020-06-18T19:48:18.651+0000",
    "due": null,
    "followUp": null,
    "delegationState": null,
    "description": null,
    "executionId": "a8661c5c-b19c-11ea-8c5f-0242ac110002",
    "owner": null,
    "parentTaskId": null,
    "priority": 50,
    "processDefinitionId": "warranty_approval_test:6:8a3c1779-b08e-11ea-8c5f-0242ac110002",
    "processInstanceId": "a8661c5c-b19c-11ea-8c5f-0242ac110002",
    "taskDefinitionKey": "Activity_1wukx49",
    "caseExecutionId": null,
    "caseInstanceId": null,
    "caseDefinitionId": null,
    "suspended": false,
    "formKey": null,
    "tenantId": null
  },
  {
    "id": "c0e7a08b-b18a-11ea-8c5f-0242ac110002",
    "name": "Validate Request",
    "assignee": "Maker",
    "created": "2020-06-18T17:40:08.823+0000",
    "due": null,
    "followUp": null,
    "delegationState": null,
    "description": null,
    "executionId": "c0e52f84-b18a-11ea-8c5f-0242ac110002",
    "owner": null,
    "parentTaskId": null,
    "priority": 50,
    "processDefinitionId": "warranty_approval_test:6:8a3c1779-b08e-11ea-8c5f-0242ac110002",
    "processInstanceId": "c0e52f84-b18a-11ea-8c5f-0242ac110002",
    "taskDefinitionKey": "Activity_1wukx49",
    "caseExecutionId": null,
    "caseInstanceId": null,
    "caseDefinitionId": null,
    "suspended": false,
    "formKey": null,
    "tenantId": null
  },
  {
    "id": "ca4a14f7-b189-11ea-8c5f-0242ac110002",
    "name": "Validate Request",
    "assignee": "Maker",
    "created": "2020-06-18T17:33:15.071+0000",
    "due": null,
    "followUp": null,
    "delegationState": null,
    "description": null,
    "executionId": "ca49eedb-b189-11ea-8c5f-0242ac110002",
    "owner": null,
    "parentTaskId": null,
    "priority": 50,
    "processDefinitionId": "warranty_approval_test:6:8a3c1779-b08e-11ea-8c5f-0242ac110002",
    "processInstanceId": "ca49eedb-b189-11ea-8c5f-0242ac110002",
    "taskDefinitionKey": "Activity_1wukx49",
    "caseExecutionId": null,
    "caseInstanceId": null,
    "caseDefinitionId": null,
    "suspended": false,
    "formKey": null,
    "tenantId": null
  },
  {
    "id": "da1d895c-b08c-11ea-8c5f-0242ac110002",
    "name": "Validate Request",
    "assignee": "Maker",
    "created": "2020-06-17T11:22:38.950+0000",
    "due": null,
    "followUp": null,
    "delegationState": null,
    "description": null,
    "executionId": "da1d6240-b08c-11ea-8c5f-0242ac110002",
    "owner": null,
    "parentTaskId": null,
    "priority": 50,
    "processDefinitionId": "warranty_approval_test:4:d77bb54f-b08c-11ea-8c5f-0242ac110002",
    "processInstanceId": "da1d6240-b08c-11ea-8c5f-0242ac110002",
    "taskDefinitionKey": "Activity_1wukx49",
    "caseExecutionId": null,
    "caseInstanceId": null,
    "caseDefinitionId": null,
    "suspended": false,
    "formKey": null,
    "tenantId": null
  },
  {
    "id": "e35cc909-b19a-11ea-8c5f-0242ac110002",
    "name": "Validate Request",
    "assignee": "Maker",
    "created": "2020-06-18T19:35:38.581+0000",
    "due": null,
    "followUp": null,
    "delegationState": null,
    "description": null,
    "executionId": "e35cc8fd-b19a-11ea-8c5f-0242ac110002",
    "owner": null,
    "parentTaskId": null,
    "priority": 50,
    "processDefinitionId": "warranty_approval_test:6:8a3c1779-b08e-11ea-8c5f-0242ac110002",
    "processInstanceId": "e35cc8fd-b19a-11ea-8c5f-0242ac110002",
    "taskDefinitionKey": "Activity_1wukx49",
    "caseExecutionId": null,
    "caseInstanceId": null,
    "caseDefinitionId": null,
    "suspended": false,
    "formKey": null,
    "tenantId": null
  },
  {
    "id": "ee04cea5-b16f-11ea-8c5f-0242ac110002",
    "name": "Validate Request",
    "assignee": "Maker",
    "created": "2020-06-18T14:28:08.100+0000",
    "due": null,
    "followUp": null,
    "delegationState": null,
    "description": null,
    "executionId": "ee048079-b16f-11ea-8c5f-0242ac110002",
    "owner": null,
    "parentTaskId": null,
    "priority": 50,
    "processDefinitionId": "warranty_approval_test:6:8a3c1779-b08e-11ea-8c5f-0242ac110002",
    "processInstanceId": "ee048079-b16f-11ea-8c5f-0242ac110002",
    "taskDefinitionKey": "Activity_1wukx49",
    "caseExecutionId": null,
    "caseInstanceId": null,
    "caseDefinitionId": null,
    "suspended": false,
    "formKey": null,
    "tenantId": null
  },
  {
    "id": "f67b0c8a-b09b-11ea-8c5f-0242ac110002",
    "name": "Validate Request",
    "assignee": "Maker",
    "created": "2020-06-17T13:10:48.990+0000",
    "due": null,
    "followUp": null,
    "delegationState": null,
    "description": null,
    "executionId": "f67abe63-b09b-11ea-8c5f-0242ac110002",
    "owner": null,
    "parentTaskId": null,
    "priority": 50,
    "processDefinitionId": "warranty_approval_test:6:8a3c1779-b08e-11ea-8c5f-0242ac110002",
    "processInstanceId": "f67abe63-b09b-11ea-8c5f-0242ac110002",
    "taskDefinitionKey": "Activity_1wukx49",
    "caseExecutionId": null,
    "caseInstanceId": null,
    "caseDefinitionId": null,
    "suspended": false,
    "formKey": null,
    "tenantId": null
  }
]
